TOPSIS/__init__.py
TOPSIS/__main__.py
Topsis_Jatin_102116096-1.0.dist-info/LICENSE
Topsis_Jatin_102116096-1.0.dist-info/METADATA
Topsis_Jatin_102116096-1.0.dist-info/WHEEL
Topsis_Jatin_102116096-1.0.dist-info/entry_points.txt
Topsis_Jatin_102116096-1.0.dist-info/top_level.txt
Topsis_Jatin_102116096-1.0.dist-info/RECORD
