Metadata-Version: 2.1
Name: Topsis-Jatin-102116096
Version: 1.0
Summary: TOPSIS implementation by Jatin Thakur
Home-page: https://github.com/Jatinthakur-1975/Topsis-Jatin_102116096
Author: Jasmeet Kaur
Author-email: jasmeet.k.2003@gmail.com
License: MIT
Classifier: License :: OSI Approved :: MIT License
Classifier: Programming Language :: Python :: 3.6
Classifier: Programming Language :: Python :: 3.7
Classifier: Programming Language :: Python :: 3.8
License-File: LICENSE
Requires-Dist: numpy
Requires-Dist: pandas
Requires-Dist: sys
